odoo9_addon_report_mrp_bom_matrix-9.0.1.0.0-py2.7-nspkg.pth
odoo9_addon_report_mrp_bom_matrix-9.0.1.0.0.dist-info/DESCRIPTION.rst
odoo9_addon_report_mrp_bom_matrix-9.0.1.0.0.dist-info/METADATA
odoo9_addon_report_mrp_bom_matrix-9.0.1.0.0.dist-info/RECORD
odoo9_addon_report_mrp_bom_matrix-9.0.1.0.0.dist-info/WHEEL
odoo9_addon_report_mrp_bom_matrix-9.0.1.0.0.dist-info/metadata.json
odoo9_addon_report_mrp_bom_matrix-9.0.1.0.0.dist-info/namespace_packages.txt
odoo9_addon_report_mrp_bom_matrix-9.0.1.0.0.dist-info/top_level.txt
odoo_addons/report_mrp_bom_matrix/README.rst
odoo_addons/report_mrp_bom_matrix/__init__.py
odoo_addons/report_mrp_bom_matrix/__openerp__.py
odoo_addons/report_mrp_bom_matrix/models/__init__.py
odoo_addons/report_mrp_bom_matrix/models/report_mrp_bom_matrix.py
odoo_addons/report_mrp_bom_matrix/security/ir.model.access.csv
odoo_addons/report_mrp_bom_matrix/views/report_mrp_bom_matrix_view.xml
